{
    "up"    : ["FW7", "FLT"],
    "down"  : ["RV7", "FLT"],
    "right" : ["FLT", "FW7"],
    "left"  : ["FLT", "RV7"],
    "space" : ["BRK", "BRK"],
    "0"   : ["FLT", "FLT"],
    "1"   : ["FW1", "FLT"],
    "2"   : ["FW2", "FLT"],
    "3"   : ["FW3", "FLT"],
    "4"   : ["FW4", "FLT"],
    "5"   : ["FW5", "FLT"],
    "6"   : ["FW6", "FLT"],
    "7"   : ["FW7", "FLT"],
    "a"   : ["RV1", "FLT"],
    "b"   : ["RV2", "FLT"],
    "c"   : ["RV3", "FLT"],
    "d"   : ["RV4", "FLT"],
    "e"   : ["RV5", "FLT"],
    "f"   : ["RV6", "FLT"],
    "g"   : ["RV7", "FLT"]
}